light_size_constrained_clustering/__init__.py
light_size_constrained_clustering/base.py
light_size_constrained_clustering/da.py
size_constrained_clustering/__init__.py
size_constrained_clustering/base.py
size_constrained_clustering/da.py
size_constrained_clustering/equal.py
size_constrained_clustering/fcm.py
size_constrained_clustering/minmax.py
size_constrained_clustering/shrinkage.py
size_constrained_clustering/sklearn_import/__init__.py
size_constrained_clustering/sklearn_import/base.py
size_constrained_clustering/sklearn_import/exceptions.py
size_constrained_clustering/sklearn_import/fixes.py
size_constrained_clustering/sklearn_import/funcsigs.py
size_constrained_clustering/sklearn_import/cluster/__init__.py
size_constrained_clustering/sklearn_import/cluster/k_means_.py
size_constrained_clustering/sklearn_import/externals/__init__.py
size_constrained_clustering/sklearn_import/externals/funcsigs.py
size_constrained_clustering/sklearn_import/metrics/__init__.py
size_constrained_clustering/sklearn_import/metrics/pairwise.py
size_constrained_clustering/sklearn_import/preprocessing/__init__.py
size_constrained_clustering/sklearn_import/preprocessing/data.py
size_constrained_clustering/sklearn_import/utils/__init__.py
size_constrained_clustering/sklearn_import/utils/extmath.py
size_constrained_clustering/sklearn_import/utils/fixes.py
size_constrained_clustering/sklearn_import/utils/sparsefuncs.py
size_constrained_clustering/sklearn_import/utils/validation.py
light_size_constrained_clustering-0.0.8.3.dist-info/LICENSE
light_size_constrained_clustering-0.0.8.3.dist-info/METADATA
light_size_constrained_clustering-0.0.8.3.dist-info/WHEEL
light_size_constrained_clustering-0.0.8.3.dist-info/requirements.txt
light_size_constrained_clustering-0.0.8.3.dist-info/top_level.txt
light_size_constrained_clustering-0.0.8.3.dist-info/RECORD
