Metadata-Version: 2.1
Name: light-size-constrained-clustering
Version: 0.0.8.3
Summary: Size Constrained Clustering solver
Home-page: https://github.com/AlbertPlaPlanas/size_constrained_clustering
Author: Albert Pla
Author-email: plaalbert@gmail.com
License: MIT
Requires-Python: >=3.6
License-File: LICENSE
Requires-Dist: joblib (>=1.2.0)
Requires-Dist: psutil (>=5.9.4)
Requires-Dist: numpy (==1.24.1)
Requires-Dist: scipy (>=1.10.0)
Requires-Dist: ortools (==9.6.2534)
Requires-Dist: six (>=1.16.0)
Requires-Dist: Cython (>=0.29.33)
Requires-Dist: scikit-learn (>=1.1.1)
